subshift/__init__.py
subshift/subshift.py
subshift/version.py
subshift-0.10.6.dist-info/LICENSE
subshift-0.10.6.dist-info/METADATA
subshift-0.10.6.dist-info/WHEEL
subshift-0.10.6.dist-info/entry_points.txt
subshift-0.10.6.dist-info/top_level.txt
subshift-0.10.6.dist-info/RECORD
